gtagora/__init__.py
gtagora/agora.py
gtagora/exception.py
gtagora/utils.py
gtagora/http/__init__.py
gtagora/http/auth.py
gtagora/http/client.py
gtagora/http/connection.py
gtagora/models/__init__.py
gtagora/models/base.py
gtagora/models/breadcrumb.py
gtagora/models/datafile.py
gtagora/models/dataset.py
gtagora/models/exam.py
gtagora/models/folder.py
gtagora/models/folder_item.py
gtagora/models/group.py
gtagora/models/host.py
gtagora/models/image_info.py
gtagora/models/import_json.py
gtagora/models/import_package.py
gtagora/models/parameter.py
gtagora/models/parameter_set.py
gtagora/models/patient.py
gtagora/models/project.py
gtagora/models/project_role.py
gtagora/models/series.py
gtagora/models/tag.py
gtagora/models/task.py
gtagora/models/timeline.py
gtagora/models/trash.py
gtagora/models/upload_session.py
gtagora/models/user.py
gtagora/models/vendor.py
gtagora/models/version.py
gtagora/models/workbook.py
gtagora_connector-1.7.3.dist-info/licenses/LICENSE
gtagora_connector-1.7.3.dist-info/METADATA
gtagora_connector-1.7.3.dist-info/WHEEL
gtagora_connector-1.7.3.dist-info/top_level.txt
gtagora_connector-1.7.3.dist-info/RECORD
