Metadata-Version: 2.4
Name: gtagora-connector
Version: 1.7.3
Summary: The Agora Connector for Python
Home-page: https://github.com/gyrotools/gtagora
Author: Martin Bührer, Felix Eichenberger
Author-email: info@gyrotools.com
Classifier: Programming Language :: Python :: 3
Classifier: License :: OSI Approved :: MIT License
Classifier: Operating System :: OS Independent
Requires-Python: >=3.6.0
License-File: LICENSE
Requires-Dist: requests>=2.0
Requires-Dist: packaging>=20.0
Requires-Dist: numpy
Dynamic: author
Dynamic: author-email
Dynamic: classifier
Dynamic: description
Dynamic: description-content-type
Dynamic: home-page
Dynamic: license-file
Dynamic: requires-dist
Dynamic: requires-python
Dynamic: summary
